ninja/__init__.py
ninja/__main__.py
ninja/_version.py
ninja/ninja_syntax.py
ninja/py.typed
ninja/data/bin/ninja.exe
mongo_ninja_python-1.11.1.6.dist-info/AUTHORS.rst
mongo_ninja_python-1.11.1.6.dist-info/LICENSE_Apache_20
mongo_ninja_python-1.11.1.6.dist-info/METADATA
mongo_ninja_python-1.11.1.6.dist-info/WHEEL
mongo_ninja_python-1.11.1.6.dist-info/entry_points.txt
mongo_ninja_python-1.11.1.6.dist-info/top_level.txt
mongo_ninja_python-1.11.1.6.dist-info/RECORD
